vendorize/__init__.py
vendorize/cli.py
vendorize/files.py
vendorize/import_rewrite.py
vendorize/python_source.py
vendorize/setuptools_build.py
vendorize/_vendor/__init__.py
vendorize/_vendor/pytoml/__init__.py
vendorize/_vendor/pytoml/core.py
vendorize/_vendor/pytoml/parser.py
vendorize/_vendor/pytoml/writer.py
vendorize-0.2.2.dist-info/LICENSE
vendorize-0.2.2.dist-info/METADATA
vendorize-0.2.2.dist-info/WHEEL
vendorize-0.2.2.dist-info/entry_points.txt
vendorize-0.2.2.dist-info/top_level.txt
vendorize-0.2.2.dist-info/RECORD
