Metadata-Version: 2.1
Name: vendorize
Version: 0.2.2
Summary: Vendorize packages from PyPI
Home-page: http://github.com/mwilliamson/python-vendorize
Author: Michael Williamson
Author-email: mike@zwobble.org
License: BSD-2-Clause
Keywords: vendor vendorize
Platform: UNKNOWN
